aiohomematic_test_support/__init__.py
aiohomematic_test_support/const.py
aiohomematic_test_support/event_capture.py
aiohomematic_test_support/event_mock.py
aiohomematic_test_support/factory.py
aiohomematic_test_support/helper.py
aiohomematic_test_support/mock.py
aiohomematic_test_support/py.typed
aiohomematic_test_support/data/device_translation.json
aiohomematic_test_support/data/full_session_randomized_ccu.zip
aiohomematic_test_support/data/full_session_randomized_pydevccu.zip
aiohomematic_test_support-2026.2.0.dist-info/METADATA
aiohomematic_test_support-2026.2.0.dist-info/WHEEL
aiohomematic_test_support-2026.2.0.dist-info/top_level.txt
aiohomematic_test_support-2026.2.0.dist-info/RECORD
