Metadata-Version: 2.4
Name: aiohomematic-test-support
Version: 2026.2.0
Summary: Support-only package for AioHomematic (tests/dev). Not part of production builds.
Author-email: SukramJ <sukramj@icloud.com>, Daniel Perna <danielperna84@gmail.com>
Project-URL: Homepage, https://github.com/SukramJ/aiohomematic
Classifier: Development Status :: 3 - Alpha
Classifier: Intended Audience :: Developers
Classifier: License :: OSI Approved :: MIT License
Classifier: Programming Language :: Python :: 3.13
Classifier: Programming Language :: Python :: 3.14
Requires-Python: >=3.13
